MANIFEST.in
README.rst
setup.py
tox.ini
docs/Makefile
docs/api.rst
docs/changelog.rst
docs/conf.py
docs/contribute.rst
docs/index.rst
docs/installation.rst
docs/showcase.rst
docs/usage.rst
rrda/__init__.py
rrda/api.py
sahuwai.egg-info/PKG-INFO
sahuwai.egg-info/SOURCES.txt
sahuwai.egg-info/dependency_links.txt
sahuwai.egg-info/not-zip-safe
sahuwai.egg-info/requires.txt
sahuwai.egg-info/top_level.txt
tests/unit.txt