Metadata-Version: 1.1
Name: sahuwai
Version: 0.1
Summary: RRDA REST DNS API client.
Home-page: http://rtfd.rop.io/sahuwai/
Author: Teguh P. Alko
Author-email: chain@rop.io
License: BSD 3-Clause License
Keywords: rest,dns,api
Platform: UNKNOWN
Classifier: Development Status :: 5 - Production/Stable
Classifier: Environment :: Console
Classifier: Intended Audience :: Developers
Classifier: License :: OSI Approved :: BSD License
Classifier: Operating System :: OS Independent
Classifier: Programming Language :: Python :: 2.7
Classifier: Topic :: Internet :: Name Service (DNS)
